{
	"schemaVersion": 1,
	"id": "testux",
	"name": "TestUX",
	"version": "${mod_version}",

	"description": "A Testing-ONLY Mod for network concepts",
	"authors": [
		"sakura-ryoko"
	],
	"contact": {
		"issues": "https://github.com/sakura-ryoko/testux/issues",
		"sources": "https://github.com/sakura-ryoko/testux"
	},

	"license": "LGPLv3",
	"icon": "assets/testux/icon.png",
	"environment": "server",
	"entrypoints": {
		"main": [
          "com.github.sakuraryoko.testux.TestUX"
		]
	},
	"mixins": [
		"mixins.testux.json"
	],

	"depends": {
		"minecraft": ">=1.21",
		"servux": ">=0.2.0.999-sakura.1"
	}
}
